{"@context":"https://iiif.io/api/presentation/3/context.json","id":"https://mathewjordan.github.io/sci-fi/api/facet/director/coleman-francis.json","type":"Collection","label":{"none":["Coleman Francis"]},"items":[{"id":"https://iiif.archive.org/iiif/Beast_of_Yucca_Flats_movie/manifest.json","type":"Manifest","label":{"none":["Beast of Yucca Flats"]},"homepage":[{"id":"https://mathewjordan.github.io/sci-fi/works/beast-of-yucca-flats","type":"Text","label":{"none":["Beast of Yucca Flats"]}}]}],"partOf":[{"id":"https://mathewjordan.github.io/sci-fi/api/facet/director.json","type":"Collection"}],"summary":{"none":["director"]},"homepage":[{"id":"https://mathewjordan.github.io/sci-fi/search?director=coleman-francis","type":"Text","label":{"none":["Coleman Francis"]}}]}